LICENSE
MANIFEST.in
README.md
requirements.txt
setup.py
test_requirements.txt
sheldonys_zappa.egg-info/PKG-INFO
sheldonys_zappa.egg-info/SOURCES.txt
sheldonys_zappa.egg-info/dependency_links.txt
sheldonys_zappa.egg-info/entry_points.txt
sheldonys_zappa.egg-info/requires.txt
sheldonys_zappa.egg-info/top_level.txt
zappa/__init__.py
zappa/async.py
zappa/asynchronous.py
zappa/cli.py
zappa/core.py
zappa/handler.py
zappa/letsencrypt.py
zappa/middleware.py
zappa/policies.py
zappa/utilities.py
zappa/wsgi.py
zappa/ext/__init__.py
zappa/ext/django_zappa.py